odoo8_addon_crm_claim_rma_code-8.0.1.0.0.99.dev10-nspkg.pth
odoo_addons/crm_claim_rma_code/README.rst
odoo_addons/crm_claim_rma_code/__init__.py
odoo_addons/crm_claim_rma_code/__openerp__.py
odoo_addons/crm_claim_rma_code/data/ir_sequence_type.xml
odoo_addons/crm_claim_rma_code/i18n/crm_claim_rma_code.pot
odoo_addons/crm_claim_rma_code/i18n/de.po
odoo_addons/crm_claim_rma_code/i18n/es.po
odoo_addons/crm_claim_rma_code/i18n/es_MX.po
odoo_addons/crm_claim_rma_code/i18n/es_PA.po
odoo_addons/crm_claim_rma_code/i18n/es_VE.po
odoo_addons/crm_claim_rma_code/i18n/pt_BR.po
odoo_addons/crm_claim_rma_code/i18n/sl.po
odoo_addons/crm_claim_rma_code/models/__init__.py
odoo_addons/crm_claim_rma_code/models/crm_claim_type.py
odoo_addons/crm_claim_rma_code/static/description/icon.png
odoo_addons/crm_claim_rma_code/views/crm_claim_type.xml
odoo8_addon_crm_claim_rma_code-8.0.1.0.0.99.dev10.dist-info/METADATA
odoo8_addon_crm_claim_rma_code-8.0.1.0.0.99.dev10.dist-info/WHEEL
odoo8_addon_crm_claim_rma_code-8.0.1.0.0.99.dev10.dist-info/namespace_packages.txt
odoo8_addon_crm_claim_rma_code-8.0.1.0.0.99.dev10.dist-info/top_level.txt
odoo8_addon_crm_claim_rma_code-8.0.1.0.0.99.dev10.dist-info/RECORD
